{
 "actions": [],
 "creation": "2026-03-25 00:00:00.000000",
 "doctype": "DocType",
 "document_type": "Document",
 "engine": "InnoDB",
 "field_order": [
  "item_code",
  "item_name",
  "description",
  "part_type",
  "column_break_1",
  "qty",
  "uom",
  "column_break_2",
  "rate",
  "amount",
  "section_break_3",
  "warehouse",
  "section_rental",
  "rental_rate",
  "rental_unit",
  "date_sortie",
  "column_break_rental",
  "date_retour",
  "is_returned"
 ],
 "fields": [
  {
   "fieldname": "item_code",
   "fieldtype": "Link",
   "in_list_view": 1,
   "label": "R\u00e9f\u00e9rence produit",
   "options": "Item",
   "reqd": 1,
   "search_index": 1
  },
  {
   "fetch_from": "item_code.item_name",
   "fieldname": "item_name",
   "fieldtype": "Data",
   "in_list_view": 1,
   "label": "D\u00e9signation",
   "read_only": 0
  },
  {
   "fieldname": "description",
   "fieldtype": "Text",
   "label": "Description"
  },
  {
   "default": "Consomm\u00e9e",
   "fieldname": "part_type",
   "fieldtype": "Select",
   "in_list_view": 1,
   "label": "Type",
   "options": "Consomm\u00e9e\nEn location"
  },
  {
   "fieldname": "column_break_1",
   "fieldtype": "Column Break"
  },
  {
   "default": "1",
   "fieldname": "qty",
   "fieldtype": "Float",
   "in_list_view": 1,
   "label": "Quantit\u00e9",
   "reqd": 1
  },
  {
   "fetch_from": "item_code.stock_uom",
   "fieldname": "uom",
   "fieldtype": "Link",
   "label": "Unit\u00e9",
   "options": "UOM"
  },
  {
   "fieldname": "column_break_2",
   "fieldtype": "Column Break"
  },
  {
   "fieldname": "rate",
   "fieldtype": "Currency",
   "in_list_view": 1,
   "label": "Prix unitaire",
   "options": "currency"
  },
  {
   "fieldname": "amount",
   "fieldtype": "Currency",
   "in_list_view": 1,
   "label": "Montant",
   "options": "currency",
   "read_only": 1
  },
  {
   "collapsible": 1,
   "fieldname": "section_break_3",
   "fieldtype": "Section Break",
   "label": "Stock"
  },
  {
   "fieldname": "warehouse",
   "fieldtype": "Link",
   "label": "Entrep\u00f4t source",
   "options": "Warehouse"
  },
  {
   "collapsible": 1,
   "depends_on": "eval: doc.part_type == 'En location'",
   "fieldname": "section_rental",
   "fieldtype": "Section Break",
   "label": "D\u00e9tails location"
  },
  {
   "depends_on": "eval: doc.part_type == 'En location'",
   "fieldname": "rental_rate",
   "fieldtype": "Currency",
   "label": "Tarif de location",
   "options": "currency"
  },
  {
   "default": "Jour",
   "depends_on": "eval: doc.part_type == 'En location'",
   "fieldname": "rental_unit",
   "fieldtype": "Select",
   "label": "Unit\u00e9",
   "options": "Jour\nSemaine\nMois"
  },
  {
   "depends_on": "eval: doc.part_type == 'En location'",
   "fieldname": "date_sortie",
   "fieldtype": "Date",
   "label": "Date de sortie",
   "no_copy": 1
  },
  {
   "fieldname": "column_break_rental",
   "fieldtype": "Column Break"
  },
  {
   "depends_on": "eval: doc.part_type == 'En location'",
   "fieldname": "date_retour",
   "fieldtype": "Date",
   "label": "Date de retour",
   "no_copy": 1
  },
  {
   "default": "0",
   "depends_on": "eval: doc.part_type == 'En location'",
   "fieldname": "is_returned",
   "fieldtype": "Check",
   "label": "Retourn\u00e9",
   "no_copy": 1,
   "read_only": 1
  }
 ],
 "istable": 1,
 "links": [],
 "modified": "2026-03-25 00:00:00.000000",
 "modified_by": "Administrator",
 "module": "Field Service",
 "name": "Field Service Parts Line",
 "owner": "Administrator",
 "permissions": [],
 "sort_field": "creation",
 "sort_order": "ASC",
 "states": []
}
